uncover/__init__.py
uncover/py.typed
uncover-0.0.0.dist-info/LICENSE
uncover-0.0.0.dist-info/METADATA
uncover-0.0.0.dist-info/WHEEL
uncover-0.0.0.dist-info/RECORD
