Metadata-Version: 2.1
Name: uncover
Version: 0.0.0
Summary: Uncover runtime objects. Enlighten your mind. Sleep soundly.
License: MIT
Author: bswck
Author-email: bswck.dev@gmail.com
Requires-Python: >=3.8,<4.0
Classifier: License :: OSI Approved :: MIT License
Classifier: Programming Language :: Python :: 3
Classifier: Programming Language :: Python :: 3.8
Classifier: Programming Language :: Python :: 3.9
Classifier: Programming Language :: Python :: 3.10
Classifier: Programming Language :: Python :: 3.11
Classifier: Programming Language :: Python :: 3.12
